safetokengen/__init__.py
safetokengen/main.py
safetokengen-0.0.5.dist-info/LICENSE
safetokengen-0.0.5.dist-info/METADATA
safetokengen-0.0.5.dist-info/WHEEL
safetokengen-0.0.5.dist-info/top_level.txt
safetokengen-0.0.5.dist-info/RECORD
