Metadata-Version: 2.1
Name: safetokengen
Version: 0.0.5
Summary: Generate Passwords, OTPs, PINs, API keys and Token lists with various options for customization.
Home-page: https://github.com/bgraphixx/safetokengen
Author: Ebubechukwu Ibeh
Author-email: Ebubechukwu Ibeh <bgraphixx5@gmail.com>
Maintainer-email: Ebubechukwu Ibeh <bgraphixx5@gmail.com>, Urias Triumph Baribefi <triumphurias@outlook.com>
License: MIT
Project-URL: Homepage, https://github.com/bgraphixx/SafeTokenGen
Project-URL: Bug Tracker, https://github.com/bgraphixx/SafeTokenGen/issues
Keywords: passwords,pins,otp,api keys
Classifier: Programming Language :: Python :: 3
Classifier: License :: OSI Approved :: MIT License
Classifier: Operating System :: OS Independent
Requires-Python: >=3.7
License-File: LICENSE
